reqe/__init__.py
reqe/api.py
reqe/exception_request.py
reqe/session.py
reqe/utils.py
reqe-2020.9.17.175617.dist-info/LICENSE
reqe-2020.9.17.175617.dist-info/METADATA
reqe-2020.9.17.175617.dist-info/WHEEL
reqe-2020.9.17.175617.dist-info/top_level.txt
reqe-2020.9.17.175617.dist-info/RECORD
