Metadata-Version: 2.1
Name: reqe
Version: 2020.9.17.175617
Summary: A python network request library that will not throw exceptions
Home-page: https://github.com/ophlr/reqe
Author: ophlr
Author-email: niushuaibing@foxmail.com
Maintainer: Eric
Maintainer-email: niushuaibing@foxmail.com
License: apache
Platform: all
Classifier: Development Status :: 5 - Production/Stable
Classifier: Intended Audience :: Developers
Classifier: License :: OSI Approved :: Apache Software License
Classifier: Programming Language :: Python :: 3
Requires-Dist: requests
